setup.py
bin/kegberry
kegberry/__init__.py
kegberry/app.py
kegberry/templates.py
kegberry.egg-info/PKG-INFO
kegberry.egg-info/SOURCES.txt
kegberry.egg-info/dependency_links.txt
kegberry.egg-info/requires.txt
kegberry.egg-info/top_level.txt