Metadata-Version: 1.0
Name: kegberry
Version: 2.1.0
Summary: Kegberry turns a Raspberry Pi into a keg monitor and digital taplist.
Home-page: http://kegberry.kegbot.org/
Author: Bevbot LLC
Author-email: info@bevbot.com
License: UNKNOWN
Platform: UNKNOWN
